phoneutria/__init__.py
phoneutria/__main__.py
phoneutria/banner.py
phoneutria/cli.py
phoneutria/colors.py
phoneutria/google_hacking.py
phoneutria/version.py
phoneutria-1.0rc28.dist-info/LICENSE
phoneutria-1.0rc28.dist-info/METADATA
phoneutria-1.0rc28.dist-info/WHEEL
phoneutria-1.0rc28.dist-info/entry_points.txt
phoneutria-1.0rc28.dist-info/top_level.txt
phoneutria-1.0rc28.dist-info/RECORD
